claude_helpers/__init__.py
claude_helpers/__main__.py
claude_helpers/cli.py
claude_helpers/config.py
claude_helpers/platform_utils.py
claude_helpers/voice.py
claude_helpers/audio/__init__.py
claude_helpers/audio/devices.py
claude_helpers/audio/recorder.py
claude_helpers/hil/__init__.py
claude_helpers/hil/core.py
claude_helpers/hil/listener.py
claude_helpers/hil/postprocessing.py
claude_helpers/hil/test.py
claude_helpers/mcp/__init__.py
claude_helpers/mcp/server.py
claude_helpers/memory_bank/__init__.py
claude_helpers/memory_bank/commands.py
claude_helpers/memory_bank/increment_models.py
claude_helpers/memory_bank/increment_utils.py
claude_helpers/memory_bank/mcp_focus.py
claude_helpers/memory_bank/mcp_main.py
claude_helpers/memory_bank/mcp_prompts.py
claude_helpers/memory_bank/mcp_resource_tools.py
claude_helpers/memory_bank/mcp_resources.py
claude_helpers/memory_bank/mcp_resources_list.py
claude_helpers/memory_bank/mcp_server.py
claude_helpers/memory_bank/mcp_server_removed.txt
claude_helpers/memory_bank/mcp_tools.py
claude_helpers/memory_bank/mcp_unified.py
claude_helpers/memory_bank/mcp_utf8_fix.py
claude_helpers/memory_bank/mcp_utf8_wrapper.py
claude_helpers/memory_bank/mcp_utils.py
claude_helpers/memory_bank/models.py
claude_helpers/memory_bank/structure.py
claude_helpers/memory_bank/template_sources/progress/dev-focus.md
claude_helpers/memory_bank/template_sources/progress/journal-template.md
claude_helpers/memory_bank/template_sources/progress/pm-focus.md
claude_helpers/memory_bank/template_sources/progress/progress-state-template.md
claude_helpers/memory_bank/template_sources/progress/tech-lead-focus.md
claude_helpers/memory_bank/template_sources/snippets/subagent_resource_access.md
claude_helpers/memory_bank/template_sources/workflow/memory-bank/ask-memory-bank.md
claude_helpers/memory_bank/template_sources/workflow/memory-bank/increment-implementation-overview.md
claude_helpers-0.2.7.dist-info/METADATA
claude_helpers-0.2.7.dist-info/WHEEL
claude_helpers-0.2.7.dist-info/entry_points.txt
claude_helpers-0.2.7.dist-info/licenses/LICENSE
claude_helpers-0.2.7.dist-info/RECORD
