Metadata-Version: 2.4
Name: claude-helpers
Version: 0.2.7
Summary: Cross-platform voice and HIL tools for Claude Code
Project-URL: Homepage, https://github.com/claude-helpers/claude-helpers
Project-URL: Repository, https://github.com/claude-helpers/claude-helpers.git
Project-URL: Issues, https://github.com/claude-helpers/claude-helpers/issues
Project-URL: Documentation, https://github.com/claude-helpers/claude-helpers/blob/main/README.md
Author-email: Vladimir Loskutov <claude-helpers@modus.dev>
License: MIT
License-File: LICENSE
Keywords: ai,claude,human-in-the-loop,transcription,voice
Classifier: Development Status :: 4 - Beta
Classifier: Intended Audience :: Developers
Classifier: License :: OSI Approved :: MIT License
Classifier: Operating System :: OS Independent
Classifier: Programming Language :: Python :: 3
Classifier: Programming Language :: Python :: 3.10
Classifier: Programming Language :: Python :: 3.11
Classifier: Programming Language :: Python :: 3.12
Classifier: Topic :: Multimedia :: Sound/Audio
Classifier: Topic :: Software Development
Requires-Python: >=3.10
Requires-Dist: claude-code-sdk>=0.0.20
Requires-Dist: click>=8.1.0
Requires-Dist: dspy>=2.5.0
Requires-Dist: fastmcp>=0.2.0
Requires-Dist: keyboard>=0.13.5
Requires-Dist: litellm[proxy]>=1.0.0
Requires-Dist: numpy>=1.24.0
Requires-Dist: openai>=1.0.0
Requires-Dist: pydantic>=2.0.0
Requires-Dist: pyyaml>=6.0.2
Requires-Dist: rich>=13.0.0
Requires-Dist: scipy>=1.10.0
Requires-Dist: sounddevice>=0.4.6
Requires-Dist: watchdog>=3.0.0
Provides-Extra: dev
Requires-Dist: mypy>=1.5.0; extra == 'dev'
Requires-Dist: pre-commit>=3.0.0; extra == 'dev'
Requires-Dist: pytest-cov>=4.0.0; extra == 'dev'
Requires-Dist: pytest-mock>=3.10.0; extra == 'dev'
Requires-Dist: pytest>=7.0.0; extra == 'dev'
Requires-Dist: ruff>=0.1.0; extra == 'dev'
Provides-Extra: linux
Requires-Dist: python-xlib>=0.33; extra == 'linux'
Provides-Extra: macos
Requires-Dist: pyobjc-framework-cocoa>=9.0; extra == 'macos'
Provides-Extra: test
Requires-Dist: pytest-cov>=4.0.0; extra == 'test'
Requires-Dist: pytest-mock>=3.10.0; extra == 'test'
Requires-Dist: pytest>=7.0.0; extra == 'test'
